<page xmlns:xsi="http://www.w3.org/2001/XMLSchema-instance" layout="1column" xsi:noNamespaceSchemaLocation="../../../../../../../lib/internal/Magento/Framework/View/Layout/etc/page_configuration.xsd">

	<head>
        <title>Become a Seller</title>
        <!-- 
		demo
		<css src="Magentomaster_Marketplace::css/css.css"/>
		<script src="Magentomaster_Marketplace::js/js.js"/>
		<css src="jquery/fileUploader/css/jquery.fileupload-ui.css"/>
		<script src="path/file.js" defer="defer"/>
		<link src="http://url.com" src_type="url"/>
		<remove src="path/remove/file.css"/>

		-->
    </head> 

    <body>


        <referenceContainer name="sidebar.main">
            <block class="Magentomaster\Marketplace\Block\Index\Sidebar" name="marketplace_index_sidebar" before="-" template="Magentomaster_Marketplace::marketplace_index_sidebar.phtml"/>
        </referenceContainer>

        <referenceContainer name="content">
            <block class="Magentomaster\Marketplace\Block\Index\Index" name="marketplace_index_index" template="Magentomaster_Marketplace::marketplace_index_index.phtml"/>
        </referenceContainer>


    </body>
</page>
